COPYING
README.rst
setup.py
SmartPipeline.egg-info/PKG-INFO
SmartPipeline.egg-info/SOURCES.txt
SmartPipeline.egg-info/dependency_links.txt
SmartPipeline.egg-info/top_level.txt
smartpipeline/__init__.py
smartpipeline/containers.py
smartpipeline/defaults.py
smartpipeline/helpers.py
smartpipeline/item.py
smartpipeline/pipeline.py
smartpipeline/py.typed
smartpipeline/runners.py
smartpipeline/stage.py
smartpipeline/utils.py
smartpipeline/error/__init__.py
smartpipeline/error/exceptions.py
smartpipeline/error/handling.py
tests/pipeline/__init__.py
tests/pipeline/test_batch.py
tests/pipeline/test_batch_concurrent.py
tests/pipeline/test_concurrent.py
tests/pipeline/test_pipeline.py