Metadata-Version: 2.1
Name: SmartPipeline
Version: 0.7.3
Summary: A framework for fast developing scalable data pipelines following a simple design pattern
Home-page: https://github.com/giacbrd/SmartPipeline
Author: Giacomo Berardi
Author-email: barnets@gmail.com
Project-URL: Documentation, https://smartpipeline.readthedocs.io
Project-URL: Source, https://github.com/giacbrd/SmartPipeline
Keywords: data pipeline,task queue,data science,machine learning,design pattern
Classifier: Topic :: Software Development
Classifier: Topic :: Scientific/Engineering
Classifier: Intended Audience :: Developers
Classifier: Intended Audience :: Science/Research
Classifier: License :: OSI Approved :: GNU Lesser General Public License v3 or later (LGPLv3+)
Classifier: Operating System :: OS Independent
Classifier: Programming Language :: Python :: 3.9
Classifier: Programming Language :: Python :: 3.10
Classifier: Programming Language :: Python :: 3.11
Classifier: Development Status :: 4 - Beta
Requires-Python: >=3.9
License-File: COPYING
